trame_facade/__init__.py
trame_facade/model/remote_file_input.py
trame_facade/view/components/__init__.py
trame_facade/view/components/input_field.py
trame_facade/view/components/remote_file_input.py
trame_facade/view/components/visualization/__init__.py
trame_facade/view/components/visualization/interactive_2d_plot.py
trame_facade/view/layouts/__init__.py
trame_facade/view/layouts/grid.py
trame_facade/view/layouts/hbox.py
trame_facade/view/layouts/vbox.py
trame_facade/view/theme/__init__.py
trame_facade/view/theme/assets/core_style.scss
trame_facade/view/theme/assets/favicon.png
trame_facade/view/theme/assets/vuetify_config.json
trame_facade/view/theme/theme.py
trame_facade/view/utilities/local_storage.py
trame_facade/view_model/remote_file_input.py
trame_facade-0.7.3.dist-info/LICENSE
trame_facade-0.7.3.dist-info/METADATA
trame_facade-0.7.3.dist-info/WHEEL
trame_facade-0.7.3.dist-info/entry_points.txt
trame_facade-0.7.3.dist-info/RECORD
