Metadata-Version: 2.1
Name: trame-facade
Version: 0.7.3
Summary: A Python Package for injecting curated themes and custom components into Trame applications
License: MIT
Keywords: NDIP,Python,Trame,Vuetify
Author: Duggan, John
Author-email: dugganjw@ornl.gov
Requires-Python: >=3.10,<4.0
Classifier: License :: OSI Approved :: MIT License
Classifier: Programming Language :: Python :: 3
Classifier: Programming Language :: Python :: 3.10
Classifier: Programming Language :: Python :: 3.11
Classifier: Programming Language :: Python :: 3.12
Classifier: Programming Language :: Python :: 3.13
Requires-Dist: libsass (>=0.23.0,<0.24.0)
Requires-Dist: mergedeep (>=1.3.4,<2.0.0)
Requires-Dist: mvvm-lib (>=0.4.0)
Requires-Dist: pydantic (>=2.10.1,<3.0.0)
Requires-Dist: tomli (>=2.0.2,<3.0.0)
Requires-Dist: trame (>=3.6.3,<4.0.0)
Requires-Dist: trame-vega (>=2.1.1,<3.0.0)
Requires-Dist: trame-vuetify (>=2.6.1,<3.0.0)
